{
    "sources": [
        {
            "DOI": "10.1093/comjnl/27.2.97",
            "ISSN": "0010-4620",
            "URL": "https://doi.org/10.1093/comjnl/27.2.97",
            "author": [
                {
                    "family": "Knuth",
                    "given": "Donald E."
                }
            ],
            "container-title": "Comput. J.",
            "id": "knuth84",
            "issue": "2",
            "issued": {
                "date-parts": [
                    [
                        1984,
                        5
                    ]
                ]
            },
            "page": "97-111",
            "publisher": "Oxford University Press, Inc.",
            "publisher-place": "USA",
            "title": "Literate programming",
            "type": "article-journal",
            "volume": "27"
        },
        {
            "DOI": "10.3828/tpr.2009.12",
            "URL": "http://www.liverpooluniversitypress.co.uk/doi/10.3828/tpr.2009.12",
            "author": [
                {
                    "family": "Batty",
                    "given": "Michael"
                },
                {
                    "family": "Marshall",
                    "given": "Stephen"
                }
            ],
            "container-title": "Town Planning Review",
            "id": "batty2009",
            "issue": "6",
            "issued": {
                "date-parts": [
                    [
                        2009,
                        11
                    ]
                ]
            },
            "language": "en",
            "note": "Number: 6",
            "page": "551-574",
            "title": "Centenary paper: <i>The evolution of cities: Geddes, Abercrombie and the new physicalism</i>",
            "title-short": "Centenary paper",
            "type": "article-journal",
            "volume": "80"
        },
        {
            "URL": "https://www.youtube.com/watch?v=UB9UVHGI6AI",
            "author": [
                {
                    "family": "Google Design"
                }
            ],
            "id": "googledesign2019",
            "issued": {
                "date-parts": [
                    [
                        2019,
                        2,
                        14
                    ]
                ]
            },
            "title": "Design is [speculative] futures design thinking - a new toolkit for preemptive design",
            "type": "article-journal"
        },
        {
            "URL": "https://journals.lww.com/neuroreport/abstract/1998/06010/restoration_of_neural_output_from_a_paralyzed.7.aspx",
            "author": [
                {
                    "family": "Kennedy",
                    "given": "P. R."
                },
                {
                    "family": "Bakay",
                    "given": "R. a. E."
                }
            ],
            "container-title": "NeuroReport",
            "id": "kennedy1998",
            "issue": "8",
            "issued": {
                "date-parts": [
                    [
                        1998,
                        6,
                        1
                    ]
                ]
            },
            "language": "en-US",
            "page": "1707",
            "title": "Restoration of neural output from a paralyzed patient by a direct brain connection",
            "type": "article-journal",
            "volume": "9"
        },
        {
            "URL": "https://www.wired.com/2002/09/vision/",
            "author": [
                {
                    "family": "Kotler",
                    "given": "Steven"
                }
            ],
            "container-title": "Wired",
            "id": "kotler",
            "language": "en-US",
            "note": "Section: tags",
            "title": "Vision quest",
            "type": "article-journal"
        },
        {
            "URL": "https://source.wustl.edu/2006/10/teenager-moves-video-icons-just-by-imagination/",
            "author": [
                {
                    "family": "Lutz",
                    "given": "Diana"
                }
            ],
            "id": "lutz2006",
            "issued": {
                "date-parts": [
                    [
                        2006,
                        10,
                        9
                    ]
                ]
            },
            "language": "en-US",
            "title": "Teenager moves video icons just by imagination - the source - washington university in st. louis",
            "type": ""
        },
        {
            "DOI": "10.15412/J.BCN.03070208",
            "URL": "https://www.ncbi.nlm.nih.gov/pmc/articles/PMC4892319/",
            "author": [
                {
                    "family": "Marzbani",
                    "given": "Hengameh"
                },
                {
                    "family": "Marateb",
                    "given": "Hamid Reza"
                },
                {
                    "family": "Mansourian",
                    "given": "Marjan"
                }
            ],
            "container-title": "Basic and Clinical Neuroscience",
            "id": "marzbani2016",
            "issue": "2",
            "issued": {
                "date-parts": [
                    [
                        2016,
                        4
                    ]
                ]
            },
            "note": "Number: 2 PMID: 27303609 PMCID: PMC4892319",
            "page": "143-158",
            "title": "Neurofeedback: A comprehensive review on system design, methodology and clinical applications",
            "title-short": "Neurofeedback",
            "type": "article-journal",
            "volume": "7"
        },
        {
            "DOI": "10.1145/2468356.2479588",
            "URL": "https://doi.org/10.1145/2468356.2479588",
            "author": [
                {
                    "family": "Long",
                    "given": "Kiel"
                },
                {
                    "family": "Vines",
                    "given": "John"
                }
            ],
            "collection-title": "CHI EA ’13",
            "id": "long2013",
            "issued": {
                "date-parts": [
                    [
                        2013,
                        4,
                        27
                    ]
                ]
            },
            "page": "29752978",
            "publisher": "Association for Computing Machinery",
            "publisher-place": "New York, NY, USA",
            "title": "Mind pool: Encouraging self-reflection through ambiguous bio-feedback",
            "title-short": "Mind pool",
            "type": "paper-conference"
        },
        {
            "URL": "https://www.youtube.com/watch?v=SvwTqnI3f4U",
            "author": [
                {
                    "family": "Laura Jade"
                }
            ],
            "id": "laurajade2015",
            "issued": {
                "date-parts": [
                    [
                        2015,
                        6,
                        4
                    ]
                ]
            },
            "note": "Directors: _:n249",
            "title": "INTERACTIVE BRAIN LIGHT illuminated by brainwaves",
            "type": "article-journal"
        },
        {
            "URL": "https://www.vice.com/en/article/gvwvb3/can-brain-scans-reveal-your-ideal-self-image",
            "author": [
                {
                    "family": "Mufson",
                    "given": "Beckett"
                }
            ],
            "id": "mufson2014",
            "issued": {
                "date-parts": [
                    [
                        2014,
                        9,
                        30
                    ]
                ]
            },
            "language": "en",
            "title": "Can Brain Scans Reveal Your Ideal Self-Image?",
            "type": ""
        }
    ],
    "project_biblios": [
        "references.bib"
    ]
}